example/__init__.py
example/manage.py
example/urls.py
example/wsgi.py
example/apps/__init__.py
example/apps/app/__init__.py
example/apps/app/models.py
example/apps/app/migrations/0001_initial.py
example/apps/app/migrations/0002_auto_20201007_1210.py
example/apps/app/migrations/0003_auto_20210604_1406.py
example/apps/app/migrations/__init__.py
example/apps/app/tests/__init__.py
example/settings/__init__.py
example/settings/base.py
example/settings/settings.py
generic_m2m_field/__init__.py
generic_m2m_field/models.py
skip_django_generic_m2m_field-0.1.0.dist-info/LICENSE
skip_django_generic_m2m_field-0.1.0.dist-info/METADATA
skip_django_generic_m2m_field-0.1.0.dist-info/WHEEL
skip_django_generic_m2m_field-0.1.0.dist-info/top_level.txt
skip_django_generic_m2m_field-0.1.0.dist-info/RECORD
