Metadata-Version: 2.1
Name: skip-django-generic-m2m-field
Version: 0.1.0
Summary: Django generic many to many field library.
Home-page: https://github.com/skip-pay/django-generic-m2m-field
Author: Lubos Matl
Author-email: matllubos@gmail.com
License: MIT
Keywords: django,fields,generic
Classifier: Development Status :: 3 - Alpha
Classifier: Environment :: Web Environment
Classifier: Framework :: Django
Classifier: Intended Audience :: Developers
Classifier: Intended Audience :: End Users/Desktop
Classifier: License :: OSI Approved :: MIT License
Classifier: Natural Language :: Czech
Classifier: Operating System :: OS Independent
Classifier: Programming Language :: Python
Classifier: Topic :: Internet :: WWW/HTTP :: Dynamic Content
Classifier: Topic :: Internet :: WWW/HTTP :: Site Management
License-File: LICENSE
Requires-Dist: django >=4.2.0
Requires-Dist: skip-django-chamber >=0.7.2
